todo_extract/__init__.py
todo_extract/__main__.py
todo_extract/main.py
todo_extract/todo_extract.py
todo_extract/version.py
todo_extract-0.2.5.dist-info/LICENSE
todo_extract-0.2.5.dist-info/WHEEL
todo_extract-0.2.5.dist-info/METADATA
todo_extract-0.2.5.dist-info/RECORD
