Metadata-Version: 2.1
Name: todo-extract
Version: 0.2.5
Summary: Extract TODO items from the text file
Home-page: https://github.com/izikeros/todo-extractor
License: MIT
Keywords: todo,todolist,todo-list,extract-todo
Author: Krystian Safjan
Author-email: ksafjan@gmail.com
Requires-Python: >=3.7
Classifier: License :: OSI Approved :: MIT License
Classifier: Programming Language :: Python
Classifier: Programming Language :: Python :: 3
Classifier: Programming Language :: Python :: 3.7
Classifier: Programming Language :: Python :: 3.8
Classifier: Programming Language :: Python :: 3.9
Classifier: Programming Language :: Python :: 3.10
Classifier: Programming Language :: Python :: 3.11
Classifier: Programming Language :: Python :: 2
Classifier: Programming Language :: Python :: 3
Project-URL: Documentation, https://github.com/izikeros/todo-extractor
Project-URL: Repository, https://github.com/izikeros/todo-extractor
